tuxsync/__init__.py
tuxsync/__main__.py
tuxsync/cli.py
tuxsync/restore.py
tuxsync/scanner.py
tuxsync/storage.py
tuxsync/utils.py
tuxsync-0.1.0.dist-info/WHEEL
tuxsync-0.1.0.dist-info/entry_points.txt
tuxsync-0.1.0.dist-info/METADATA
tuxsync-0.1.0.dist-info/RECORD
