Metadata-Version: 2.3
Name: tuxsync
Version: 0.1.0
Summary: A Linux CLI tool for syncing packages and configurations across machines - like Migration Assistant for Linux
Keywords: linux,dotfiles,sync,cli,profile,backup,restore
Author: Gururagavendra85
Author-email: Gururagavendra85 <gururagavendra.v@rapyuta-robotics.com>
Classifier: Development Status :: 3 - Alpha
Classifier: Environment :: Console
Classifier: Intended Audience :: Developers
Classifier: Intended Audience :: System Administrators
Classifier: License :: OSI Approved :: MIT License
Classifier: Operating System :: POSIX :: Linux
Classifier: Programming Language :: Python :: 3
Classifier: Programming Language :: Python :: 3.10
Classifier: Programming Language :: Python :: 3.11
Classifier: Programming Language :: Python :: 3.12
Classifier: Topic :: System :: Systems Administration
Requires-Dist: pyyaml>=6.0
Requires-Dist: requests>=2.31
Requires-Dist: click>=8.1
Requires-Dist: rich>=13.0
Requires-Dist: build>=1.3.0
Requires-Dist: pytest>=7.0 ; extra == 'dev'
Requires-Dist: pytest-cov>=4.0 ; extra == 'dev'
Requires-Dist: ruff>=0.1 ; extra == 'dev'
Requires-Dist: mypy>=1.0 ; extra == 'dev'
Requires-Dist: pre-commit>=3.0 ; extra == 'dev'
Requires-Python: >=3.10
Project-URL: Homepage, https://github.com/Gururagavendra/tuxsync
Project-URL: Issues, https://github.com/Gururagavendra/tuxsync/issues
Project-URL: Repository, https://github.com/Gururagavendra/tuxsync
Provides-Extra: dev
